formol.py
formol-0.9.0.dist-info/METADATA
formol-0.9.0.dist-info/WHEEL
formol-0.9.0.dist-info/RECORD
