Metadata-Version: 2.1
Name: formol
Version: 0.9.0
Summary: Plain text beautifier
Home-page: https://github.com/eepp/formol/
License: MIT
Author: Philippe Proulx
Author-email: eeppeliteloop@gmail.com
Requires-Python: >=3.8,<4.0
Classifier: Development Status :: 4 - Beta
Classifier: Intended Audience :: Developers
Classifier: License :: OSI Approved :: MIT License
Classifier: Operating System :: OS Independent
Classifier: Programming Language :: Python :: 3
Classifier: Programming Language :: Python :: 3.8
Classifier: Programming Language :: Python :: 3.9
Classifier: Programming Language :: Python :: 3.10
Classifier: Programming Language :: Python :: 3.11
Classifier: Programming Language :: Python :: 3.12
Classifier: Topic :: Software Development :: Documentation
Project-URL: Bug tracker, https://github.com/eepp/formol/issues/
Project-URL: Repository, https://github.com/eepp/formol/
